biasmonitor/config/config.ini
biasmonitor/config/constants.py
biasmonitor/fairness/__init__.py
biasmonitor/fairness/credit_scoring.py
biasmonitor/fairness/customer_marketing.py
biasmonitor/fairness/fairness.py
biasmonitor/metrics/__init__.py
biasmonitor/metrics/fairness_metrics.py
biasmonitor/metrics/modelrates.py
biasmonitor/metrics/newmetric.py
biasmonitor/metrics/performance_metrics.py
biasmonitor/metrics/tradeoff.py
biasmonitor/model/__init__.py
biasmonitor/model/model_container.py
biasmonitor/model/modelwrapper.py
biasmonitor/resources/data/credit_score_dict.pickle
biasmonitor/resources/data/credit_score_sample.pickle
biasmonitor/resources/widget/fair_class_jpg.JPG
biasmonitor/resources/widget/fair_regression_jpg.JPG
biasmonitor/resources/widget/fair_uplift_jpg.JPG
biasmonitor/resources/widget/perf_class_jpg.JPG
biasmonitor/resources/widget/perf_regression_jpg.JPG
biasmonitor/resources/widget/perf_uplift_jpg.JPG
biasmonitor/util/errors.py
biasmonitor/util/utility.py
biasmonitor-1.0.14.dist-info/METADATA
biasmonitor-1.0.14.dist-info/WHEEL
biasmonitor-1.0.14.dist-info/license.txt
biasmonitor-1.0.14.dist-info/top_level.txt
biasmonitor-1.0.14.dist-info/RECORD
