Metadata-Version: 2.1
Name: biasmonitor
Version: 1.0.14
Summary: BiasMonitor Diagnosis tool for fairness assessment.
Author: MAS BiasMonitor
Requires-Python: >=3.9.5
License-File: license.txt
Requires-Dist: numpy (==1.22.0)
Requires-Dist: scipy (==1.7.1)
Requires-Dist: scikit-learn (==0.24.2)
Requires-Dist: pandas (==1.3.2)
Requires-Dist: ipywidgets (==7.6.4)
Requires-Dist: IPython (==7.31.1)
Requires-Dist: matplotlib (==3.4.3)
Requires-Dist: tqdm (==4.62.2)
Requires-Dist: pytest (==6.2.5)
Requires-Dist: pywin32
